splunksecrets/__init__.py
splunksecrets/cli.py
splunksecrets/dbconnect.py
splunksecrets/phantom.py
splunksecrets/splunk.py
splunksecrets-1.1.0.dist-info/METADATA
splunksecrets-1.1.0.dist-info/WHEEL
splunksecrets-1.1.0.dist-info/entry_points.txt
splunksecrets-1.1.0.dist-info/RECORD
