Metadata-Version: 2.4
Name: splunksecrets
Version: 1.1.0
Summary: Command-line tools for working with secrets for Splunk products
Author: Steve McMaster, Cameron Schmidt
Maintainer: Cameron Schmidt
Requires-Python: >=3.9
Requires-Dist: click>=8.0.0
Requires-Dist: cryptography>=43
Requires-Dist: pcrypt
